README.md
setup.cfg
setup.py
visguy_probability/Binomialdistribution.py
visguy_probability/Gaussiandistribution.py
visguy_probability/Generaldistribution.py
visguy_probability/__init__.py
visguy_probability.egg-info/PKG-INFO
visguy_probability.egg-info/SOURCES.txt
visguy_probability.egg-info/dependency_links.txt
visguy_probability.egg-info/not-zip-safe
visguy_probability.egg-info/top_level.txt