Metadata-Version: 1.0
Name: visguy-probability
Version: 1.1
Summary: Gaussian distributions by visguy
Home-page: UNKNOWN
Author: Amir Smajevic
Author-email: visocicaguy@gmail.com
License: UNKNOWN
Platform: UNKNOWN
